tomlify/__init__.py
tomlify/lexer/__init__.py
tomlify/lexer/base_lexer.py
tomlify/lexer/comment_lexer.py
tomlify/lexer/date_lexer.py
tomlify/lexer/exceptions.py
tomlify/lexer/identifier_lexer.py
tomlify/lexer/lex_runner.py
tomlify/lexer/lex_token.py
tomlify/lexer/lexer.py
tomlify/lexer/number_lexer.py
tomlify/lexer/string_lexer.py
tomlify/lexer/token_type.py
tomlify/parser/__init__.py
tomlify/parser/abnf.txt
tomlify/parser/exceptions.py
tomlify/parser/expr.py
tomlify/parser/parse_runner.py
tomlify/parser/parser.py
tomlify/utils/__init__.py
tomlify/utils/regex.py
tomlify-0.1.0.dist-info/METADATA
tomlify-0.1.0.dist-info/WHEEL
tomlify-0.1.0.dist-info/RECORD
