Metadata-Version: 2.4
Name: tomlify
Version: 0.1.0
Summary: Add your description here
Author-email: Todd Doughty <w.todd.doughty@gmail.com>
Requires-Python: >=3.10
Requires-Dist: click<8.2.0
Requires-Dist: typer>=0.15.3
